Metadata-Version: 1.1
Name: django-feedreader
Version: 2.3.0
Summary: A simple Django app to aggregate RSS feeds.
Home-page: https://github.com/ahernp/django-feedreader
Author: Paul Ahern
Author-email: ahernp@ahernp.com
License: BSD License
Platform: UNKNOWN
Classifier: Environment :: Web Environment
Classifier: Framework :: Django
Classifier: Intended Audience :: Developers
Classifier: License :: OSI Approved :: BSD License
Classifier: Operating System :: OS Independent
Classifier: Programming Language :: Python :: 3.6
